pyfronius/__init__.py
pyfronius/const.py
pyfronius/py.typed
pyfronius-0.8.1.dist-info/licenses/LICENSE.txt
pyfronius-0.8.1.dist-info/METADATA
pyfronius-0.8.1.dist-info/WHEEL
pyfronius-0.8.1.dist-info/top_level.txt
pyfronius-0.8.1.dist-info/RECORD
