Metadata-Version: 2.4
Name: PyFronius
Version: 0.8.1
Summary: Client for Fronius SolarAPI JSON interface
Author-email: Niels Mündler <n.muendler@web.de>, Matthias Alphart <farmio@alphart.net>, Gerrit Beine <mail@gerritbeine.de>
License: MIT
Project-URL: Repository, https://github.com/nielstron/pyfronius/
Keywords: Fronius,SolarAPI,photovoltaics,pv
Classifier: Programming Language :: Python :: 3.8
Classifier: Programming Language :: Python :: 3.9
Classifier: Programming Language :: Python :: 3.10
Classifier: Programming Language :: Python :: 3.11
Classifier: Programming Language :: Python :: 3.12
Classifier: Programming Language :: Python :: 3.13
Classifier: Operating System :: OS Independent
Classifier: License :: OSI Approved :: MIT License
Classifier: Development Status :: 3 - Alpha
Classifier: Intended Audience :: Developers
Classifier: Topic :: Software Development :: Object Brokering
Requires-Python: >=3.8.0
License-File: LICENSE.txt
Requires-Dist: aiohttp
Dynamic: license-file
